alu.v
module alu (
    input  [3:0] a,
    input  [3:0] b,
    input  [2:0] sel,
    output reg [4:0] y
);

always @(*) begin
    case(sel)
        3'b000: y = a + b;
        3'b001: y = a - b;
        3'b010: y = {1'b0,(a & b)};
        3'b011: y = {1'b0,(a | b)};
        3'b100: y = {1'b0,(a ^ b)};
        3'b101: y = {1'b0,(~(a | b))};
        3'b110: y = (a > b) ? 5'b00001 : 5'b00000;
        3'b111: y = (a == b) ? 5'b00001 : 5'b00000;
        default: y = 5'b00000;
    endcase
end

endmodule

tb.v


module tb;

reg  [3:0] a;
reg  [3:0] b;
reg  [2:0] sel;
wire [4:0] y;

alu dut (
    .a(a),
    .b(b),
    .sel(sel),
    .y(y)
);

initial begin
    $dumpfile("alu.vcd");
    $dumpvars(0, tb);

    a = 4'd8; b = 4'd3;

    sel = 3'b000; #10; // Add
    sel = 3'b001; #10; // Sub
    sel = 3'b010; #10; // AND
    sel = 3'b011; #10; // OR
    sel = 3'b100; #10; // XOR
    sel = 3'b101; #10; // NOR
    sel = 3'b110; #10; // Greater
    sel = 3'b111; #10; // Equal

    $finish;
end

initial begin
    $monitor("time=%0t a=%d b=%d sel=%b y=%d",
              $time,a,b,sel,y);
end

endmodule

alu.vcd
$version Generated by VerilatedVcd $end
$timescale 1ps $end
 $scope module tb $end
  $var wire 4 " a [3:0] $end
  $var wire 4 # b [3:0] $end
  $var wire 3 $ sel [2:0] $end
  $var wire 5 % y [4:0] $end
  $scope module dut $end
   $var wire 4 " a [3:0] $end
   $var wire 4 # b [3:0] $end
   $var wire 3 $ sel [2:0] $end
   $var wire 5 % y [4:0] $end
  $upscope $end
 $upscope $end
$enddefinitions $end


#0
b1000 "
b0011 #
b000 $
b01011 %
#10
b001 $
b00101 %
#20
b010 $
b00000 %
#30
b011 $
b01011 %
#40
b100 $
#50
b101 $
b00100 %
#60
b110 $
b00001 %
#70
b111 $
b00000 %
